MANIFEST.in
README.txt
setup.cfg
setup.py
medialog/.DS_Store
medialog/__init__.py
medialog.roundskin.egg-info/PKG-INFO
medialog.roundskin.egg-info/SOURCES.txt
medialog.roundskin.egg-info/dependency_links.txt
medialog.roundskin.egg-info/entry_points.txt
medialog.roundskin.egg-info/namespace_packages.txt
medialog.roundskin.egg-info/not-zip-safe
medialog.roundskin.egg-info/paster_plugins.txt
medialog.roundskin.egg-info/requires.txt
medialog.roundskin.egg-info/top_level.txt
medialog/roundskin/.DS_Store
medialog/roundskin/__init__.py
medialog/roundskin/configure.zcml
medialog/roundskin/profiles.zcml
medialog/roundskin/setuphandlers.py
medialog/roundskin/skins.zcml
medialog/roundskin/tests.py
medialog/roundskin/version.txt
medialog/roundskin/browser/.DS_Store
medialog/roundskin/browser/__init__.py
medialog/roundskin/browser/configure.zcml
medialog/roundskin/browser/interfaces.py
medialog/roundskin/browser/viewlet.pt
medialog/roundskin/browser/viewlets.py
medialog/roundskin/browser/images/README.txt
medialog/roundskin/browser/stylesheets/README.txt
medialog/roundskin/browser/stylesheets/main.css
medialog/roundskin/locales/README.txt
medialog/roundskin/profiles/.DS_Store
medialog/roundskin/profiles/default/.DS_Store
medialog/roundskin/profiles/default/cssregistry.xml
medialog/roundskin/profiles/default/jsregistry.xml
medialog/roundskin/profiles/default/medialog.roundskin_various.txt
medialog/roundskin/profiles/default/metadata.xml
medialog/roundskin/profiles/default/skins.xml
medialog/roundskin/profiles/default/viewlets.xml
medialog/roundskin/skins/.DS_Store
medialog/roundskin/skins/medialog_roundskin_custom_images/.DS_Store
medialog/roundskin/skins/medialog_roundskin_custom_images/CONTENT.txt
medialog/roundskin/skins/medialog_roundskin_custom_images/menuFundo.jpg
medialog/roundskin/skins/medialog_roundskin_custom_images/menuItemNormalDir.gif
medialog/roundskin/skins/medialog_roundskin_custom_images/menuItemNormalEsq.gif
medialog/roundskin/skins/medialog_roundskin_custom_images/menuItemNormalFundo.gif
medialog/roundskin/skins/medialog_roundskin_custom_images/menuItemNormalSeletor.gif
medialog/roundskin/skins/medialog_roundskin_custom_images/menuItemSelecionadoDir.gif
medialog/roundskin/skins/medialog_roundskin_custom_images/menuItemSelecionadoEsq.gif
medialog/roundskin/skins/medialog_roundskin_custom_images/menuItemSelecionadoFundo.gif
